bashful
