Metadata-Version: 1.1
Name: bashful
Version: 0.0.4
Summary: Because your bash scripts should be quiet and shy (and not such a loudmouth)
Home-page: https://github.com/wagoodman/bashful
Author: Alex Goodman
Author-email: wagoodman@gmail.com
License: MIT
Keywords: bash
Platform: linux
Classifier: Development Status :: 4 - Beta
Classifier: Environment :: Console
Classifier: Intended Audience :: Developers
Classifier: License :: OSI Approved :: MIT License
Classifier: Natural Language :: English
Classifier: Operating System :: POSIX :: Linux
Classifier: Programming Language :: Python
Classifier: Programming Language :: Python :: 2
Classifier: Programming Language :: Python :: 3
Classifier: Programming Language :: Python :: Implementation :: CPython
Classifier: Topic :: Software Development :: Libraries :: Python Modules
Classifier: Topic :: System :: Systems Administration
Classifier: Topic :: System :: System Shells
Classifier: Topic :: Terminals
Classifier: Topic :: Utilities
